MANIFEST.in
README.rst
setup.py
bin/hamb
hamb/__init__.py
hamb/__version__.py
hamb/athena_comp.py
hamb/config_wrapper.py
hamb/ham_run_utility.py
hamb/module.py
hamb/sql_comp.py
hamb/sql_comp_list.py
hamb/startup_banner.txt
hamb.egg-info/PKG-INFO
hamb.egg-info/SOURCES.txt
hamb.egg-info/dependency_links.txt
hamb.egg-info/requires.txt
hamb.egg-info/top_level.txt
hamb/config/services.yaml
hamb/handlers/__init__.py
hamb/handlers/email_handler.py
hamb/handlers/jenkins_handler.py
hamb/handlers/sample_test_failed_handler.py
hamb/handlers/sample_test_handler.py
hamb/handlers/sftp_handler.py
hamb/handlers/slack_handler.py
hamb/handlers/sns_handler.py
hamb/handlers/watch_file_handler.py
hamb/manifests/sample.yaml
hamb/manifests/sample_compare.yaml
hamb/manifests/sample_compare_list.yaml