Metadata-Version: 2.1
Name: hamb
Version: 0.1.8
Summary: UNKNOWN
Home-page: https://github.com/equinoxfitness/HAMB
Author: Equinox Fitness
License: TBD
Platform: UNKNOWN
Classifier: Development Status :: 5 - Production/Stable
Classifier: Intended Audience :: Developers
Classifier: Natural Language :: English
Classifier: License :: OSI Approved :: MIT License
Classifier: Programming Language :: Python :: 3.6
